{
  "name": "<%= name %>",
  "version": "0.1.0",
  "private": true,
  "scripts": {
    "dev": "run-p dev:*",
    "dev:front": "nuxt-ts",
    "dev:server": "webpack --watch --mode=development --config server/webpack.config.js",
    "dev:aspida": "aspida --watch",
    "dev:frourio": "frourio --watch",
    "build": "npm run build:apis && run-p build:front build:server",
    "build:front": "nuxt-ts build",
    "build:server": "webpack --mode=production --config server/webpack.config.js",
    "build:apis": "cross-env NODE_ENV=production run-p build:aspida build:frourio",
    "build:aspida": "aspida --build",
    "build:frourio": "frourio --build",
    "lint": "npm run lint:script && npm run lint:style",
    "lint:script": "eslint --ext .ts,.js,.vue --ignore-path .gitignore .",
    "lint:style": "stylelint \"**/*.{*(s)css,vue}\"",
    "lint:fix": "npm run lint:script -- --fix && npm run lint:style -- --fix",
    "typecheck": "npm run build:apis && tsc --noEmit",
    "start": "run-p start:*",
    "start:front": "nuxt-ts start",
    "start:server": "cross-env NODE_ENV=production node server/index.js"
  },
  "lint-staged": {
    "*.{js,vue}": "yarn lint",
    "*.{css,vue}": "stylelint"
  },
  "husky": {
    "hooks": {
      "pre-commit": "lint-staged"
    }
  },
  "dependencies": {
    "@aspida/axios": "^0.8.0",
    "@nuxt/typescript-runtime": "^0.4.8",
    "@nuxtjs/axios": "^5.3.6",
    "dotenv": "^8.2.0",
    "frourio": "^0.9.0",
    "nuxt": "2.12.2",
    "passport": "^0.4.1",
    "passport-trusted-header": "^1.1.0"
  },
  "devDependencies": {
    "@nuxt/components": "^0.3.3",
    "@nuxt/typescript-build": "^1.0.3",
    "@nuxtjs/eslint-config-typescript": "^1.0.0",
    "@nuxtjs/eslint-module": "^1.0.0",
    "@nuxtjs/stylelint-module": "^3.1.0",
    "@types/passport": "^1.0.3",
    "babel-eslint": "^10.0.1",
    "cross-env": "^7.0.2",
    "eslint": "^6.1.0",
    "eslint-config-prettier": "^6.10.0",
    "eslint-plugin-nuxt": ">=0.4.2",
    "eslint-plugin-prettier": "^3.1.2",
    "husky": "^4.0.0",
    "lint-staged": "^10.0.0",
    "nodemon-webpack-plugin": "^4.3.1",
    "npm-run-all": "^4.1.5",
    "prettier": "^1.19.1",
    "stylelint": "^10.1.0",
    "ts-loader": "^7.0.5",
    "ts-node": "^8.10.2",
    "tsconfig-paths-webpack-plugin": "^3.2.0",
    "typescript": "^3.9.5",
    "webpack-cli": "^3.3.11"
  }
}
